BeetleETL/DaemonHandler.py
BeetleETL/__init__.py
BeetleETL/Handlers/ConfigHandler.py
BeetleETL/Handlers/ETLHandler.py
BeetleETL/Handlers/MongoHandler.py
BeetleETL/Handlers/Package.py
BeetleETL/Handlers/SQLHandler.py
BeetleETL/Handlers/__init__.py
BeetleETL/tests/__init__.py
BeetleETL/tests/test_config.py
BeetleETL/tests/test_etl.py
BeetleETL/tests/test_mongo.py
BeetleETL/tests/test_sql.py
BeetleETL-1.0.4.data/scripts/beetle
BeetleETL-1.0.4.dist-info/METADATA
BeetleETL-1.0.4.dist-info/RECORD
BeetleETL-1.0.4.dist-info/WHEEL
BeetleETL-1.0.4.dist-info/top_level.txt
