Metadata-Version: 2.1
Name: BeetleETL
Version: 1.0.4
Summary: Open Source python package for moving data from NoSQL to relational databases.
Home-page: https://gitlab.com/Open-Interject/Beetle-ETL
Author: Robby Boney & Jonathon Carothers
Author-email: robbyb@gointerject.com
License: Apache License
Platform: UNKNOWN
Requires-Python: >=3
Requires-Dist: pymongo (>=3.6.0)
Requires-Dist: pyodbc (>=4.0.23)
